odoo/addons/ssi_l10n_id_partner_identification_bpjs/README.rst
odoo/addons/ssi_l10n_id_partner_identification_bpjs/__init__.py
odoo/addons/ssi_l10n_id_partner_identification_bpjs/__manifest__.py
odoo/addons/ssi_l10n_id_partner_identification_bpjs/data/res_partner_id_category_data.xml
odoo/addons/ssi_l10n_id_partner_identification_bpjs/models/__init__.py
odoo/addons/ssi_l10n_id_partner_identification_bpjs/models/res_partner.py
odoo/addons/ssi_l10n_id_partner_identification_bpjs/static/description/icon.png
odoo14_addon_ssi_l10n_id_partner_identification_bpjs-14.0.1.0.2.dev1.dist-info/METADATA
odoo14_addon_ssi_l10n_id_partner_identification_bpjs-14.0.1.0.2.dev1.dist-info/WHEEL
odoo14_addon_ssi_l10n_id_partner_identification_bpjs-14.0.1.0.2.dev1.dist-info/top_level.txt
odoo14_addon_ssi_l10n_id_partner_identification_bpjs-14.0.1.0.2.dev1.dist-info/RECORD
